opentelemetry/instrumentation/dbapi/__init__.py
opentelemetry/instrumentation/dbapi/package.py
opentelemetry/instrumentation/dbapi/version.py
sw_apm_opentelemetry_instrumentation_dbapi-0.45b0.dist-info/METADATA
sw_apm_opentelemetry_instrumentation_dbapi-0.45b0.dist-info/WHEEL
sw_apm_opentelemetry_instrumentation_dbapi-0.45b0.dist-info/licenses/LICENSE
sw_apm_opentelemetry_instrumentation_dbapi-0.45b0.dist-info/RECORD
